{"cameraMode":{"drawMode":0,"name":"Shaded","section":"Shading Mode"},"sceneLighting":true,"audioPlay":false,"sceneViewState":{"m_AlwaysRefresh":false,"showFog":true,"showSkybox":true,"showFlares":true,"showImageEffects":true,"showParticleSystems":true,"showVisualEffectGraphs":true,"m_FxEnabled":true},"in2DMode":false,"pivot":{"x":-1.296931505203247,"y":3.1752445697784426,"z":-3.7693161964416506},"rotation":{"x":-0.3743426501750946,"y":-0.1425207406282425,"z":0.05834294855594635,"w":-0.9144216179847717},"size":0.9626563787460327,"orthographic":false}